README.md
setup.py
turtleplotlib/__init__.py
turtleplotlib.egg-info/PKG-INFO
turtleplotlib.egg-info/SOURCES.txt
turtleplotlib.egg-info/dependency_links.txt
turtleplotlib.egg-info/top_level.txt
turtleplotlib.egg-info/zip-safe