Metadata-Version: 1.0
Name: turtleplotlib
Version: 0.1.0
Summary: Graphic Turtle to be used within a Matplotlib Figure
Home-page: http://github.com/jsbueno/turtleplotlib
Author: João S. O. Bueno
Author-email: gwidion@gmail.com
License: LGPLv3
Platform: UNKNOWN
